{
    "bundles": [
        {
            "bundle_name": "StarHub_sg",
            "sha1": "7779238a8935ebc8e7e92f591cff5824b2544959",
            "file_size": 20480,
            "created_at": "2025-05-22T19:41:37.661483+00:00"
        },
        {
            "bundle_name": "Vodafone_pt",
            "sha1": "bcf1cdb1c956a3dddf88247a4c3056a7dbc63807",
            "file_size": 30720,
            "created_at": "2025-05-22T19:41:37.665262+00:00"
        },
        {
            "bundle_name": "vivo_br",
            "sha1": "945b8eeda729c51ba9edb64aefd8cfdd8f6db788",
            "file_size": 20480,
            "created_at": "2025-05-22T19:41:37.670777+00:00"
        },
        {
            "bundle_name": "ATT_aio_US",
            "sha1": "98c1c9c03af6ae4ac0b373cc0eefc0623a6a42a3",
            "file_size": 30720,
            "created_at": "2025-05-22T19:41:37.674751+00:00"
        },
        {
            "bundle_name": "Ncell_np",
            "sha1": "03c0218b5a1adaa678cdecdec03c7a0f200d37c5",
            "file_size": 20480,
            "created_at": "2025-05-22T19:41:37.676253+00:00"
        },
        {
            "bundle_name": "TMobile_US",
            "sha1": "c2cf4a819f09b17af774733f85c6e9da7f3fae44",
            "file_size": 40960,
            "created_at": "2025-05-22T19:41:37.678527+00:00"
        },
        {
            "bundle_name": "Softbank_jp",
            "sha1": "096d3eba5b7379948974afe6d0abe7ec007a693d",
            "file_size": 245760,
            "created_at": "2025-05-22T19:41:37.695083+00:00"
        },
        {
            "bundle_name": "Verizon_Credo_LTE_US",
            "sha1": "965f9cb7e166286ab6706d46f3e19088052f34b1",
            "file_size": 51200,
            "created_at": "2025-05-22T19:41:37.698007+00:00"
        },
        {
            "bundle_name": "Orange_il",
            "sha1": "fc1bcc7e1eb755889b77b6df3d4bb4b275d78ffe",
            "file_size": 20480,
            "created_at": "2025-05-22T19:41:37.699131+00:00"
        },
        {
            "bundle_name": "TIM_br",
            "sha1": "63e626251b5085bdbf7b0ad961dd95b7a308053e",
            "file_size": 20480,
            "created_at": "2025-05-22T19:41:37.700488+00:00"
        },
        {
            "bundle_name": "DiGi_my",
            "sha1": "84dfb5e84eabf670ebe14e97de88508a40c3356e",
            "file_size": 20480,
            "created_at": "2025-05-22T19:41:37.702314+00:00"
        },
        {
            "bundle_name": "2degrees_nz",
            "sha1": "aea8cb0507a67bd93b6b93739e43e009aad3fd10",
            "file_size": 20480,
            "created_at": "2025-05-22T19:41:37.703484+00:00"
        },
        {
            "bundle_name": "O2_ie",
            "sha1": "685a3e54f820bef5e5b53f5de2beadbb30b492ca",
            "file_size": 30720,
            "created_at": "2025-05-22T19:41:37.705351+00:00"
        },
        {
            "bundle_name": "KDDI_LTE_jp",
            "sha1": "93388abc9a4982eb0a72d0d15228aa65d24f240f",
            "file_size": 40960,
            "created_at": "2025-05-22T19:41:37.707657+00:00"
        },
        {
            "bundle_name": "MTS_ca",
            "sha1": "88757f07b7019936a207f4f018e261862bff858a",
            "file_size": 20480,
            "created_at": "2025-05-22T19:41:37.709021+00:00"
        },
        {
            "bundle_name": "8ta_za",
            "sha1": "b953a1798e2fef5c638148622d205f2b65762539",
            "file_size": 20480,
            "created_at": "2025-05-22T19:41:37.710123+00:00"
        },
        {
            "bundle_name": "BhartiAirtel_in",
            "sha1": "e0cb80fa9f7441926c83748461a65c4292216045",
            "file_size": 30720,
            "created_at": "2025-05-22T19:41:37.711995+00:00"
        },
        {
            "bundle_name": "MTS_ru",
            "sha1": "4e446700c6c8eefccce3d1e8bd73440ae0fb9362",
            "file_size": 30720,
            "created_at": "2025-05-22T19:41:37.713815+00:00"
        },
        {
            "bundle_name": "TimorTelecom_tl",
            "sha1": "0fe63ae435d11fe177107d16727af8687904309d",
            "file_size": 20480,
            "created_at": "2025-05-22T19:41:37.714903+00:00"
        },
        {
            "bundle_name": "VinaPhone_vn",
            "sha1": "e149c367cd68c41f94580fc385802927252b06ac",
            "file_size": 20480,
            "created_at": "2025-05-22T19:41:37.715989+00:00"
        },
        {
            "bundle_name": "Zong_pk",
            "sha1": "98785f5b31510db4a20e958f8ac2e47c111c6169",
            "file_size": 20480,
            "created_at": "2025-05-22T19:41:37.717305+00:00"
        },
        {
            "bundle_name": "Orange_pl",
            "sha1": "9f4020035d82b5e09c2dfecb14d0d8d8487ff8fb",
            "file_size": 30720,
            "created_at": "2025-05-22T19:41:37.719106+00:00"
        },
        {
            "bundle_name": "Qtel_tn",
            "sha1": "b855558093f717f9b9398467791c39dfe077323f",
            "file_size": 20480,
            "created_at": "2025-05-22T19:41:37.720176+00:00"
        },
        {
            "bundle_name": "Claro_ar",
            "sha1": "209aa22135b5cdb8dc1fdf7083467ca7e0f612e6",
            "file_size": 20480,
            "created_at": "2025-05-22T19:41:37.721555+00:00"
        },
        {
            "bundle_name": "GigSky_SIM_US",
            "sha1": "72a18f0ff6a296bd23dd6a73f1effd480914d1f5",
            "file_size": 30720,
            "created_at": "2025-05-22T19:41:37.722890+00:00"
        },
        {
            "bundle_name": "movistar_ar",
            "sha1": "3db1c364944b01a9ea5534dd7cfc9cfe12977f86",
            "file_size": 20480,
            "created_at": "2025-05-22T19:41:37.724232+00:00"
        },
        {
            "bundle_name": "TaiwanMobile_tw",
            "sha1": "df94a0a2d35dad6fe576a08a5f315e52fa0a9714",
            "file_size": 30720,
            "created_at": "2025-05-22T19:41:37.725823+00:00"
        },
        {
            "bundle_name": "Telenor_dk",
            "sha1": "cdbe23924f169493d903e29fd9c89e4111733e7f",
            "file_size": 20480,
            "created_at": "2025-05-22T19:41:37.726932+00:00"
        },
        {
            "bundle_name": "GCI_US",
            "sha1": "5efb982167b4d27bd1c378cb7d768d32b466bf47",
            "file_size": 20480,
            "created_at": "2025-05-22T19:41:37.728015+00:00"
        },
        {
            "bundle_name": "EE_Virgin_uk",
            "sha1": "c5c226e68ce830028bd8003e18537113dfaaac66",
            "file_size": 20480,
            "created_at": "2025-05-22T19:41:37.729081+00:00"
        },
        {
            "bundle_name": "Fido_ca",
            "sha1": "a01c99b33cacb5d1fa856c6b7adc632977a6ad28",
            "file_size": 30720,
            "created_at": "2025-05-22T19:41:37.730908+00:00"
        },
        {
            "bundle_name": "Pioneer_LTE_US",
            "sha1": "46e5102432bf41e0a0d27eb91fa0604d06b94d2a",
            "file_size": 40960,
            "created_at": "2025-05-22T19:41:37.733171+00:00"
        },
        {
            "bundle_name": "Bootstrap_Truphone_US",
            "sha1": "a373ea6b5ae97cc01be2694dc86ad2362fdab4bf",
            "file_size": 20480,
            "created_at": "2025-05-22T19:41:37.735255+00:00"
        },
        {
            "bundle_name": "Yoigo_es",
            "sha1": "328782d7db414aae64783b2edbcfa5284a1ae580",
            "file_size": 20480,
            "created_at": "2025-05-22T19:41:37.738043+00:00"
        },
        {
            "bundle_name": "Personal_ar",
            "sha1": "36119febfe39ece1521c077afda881033ebd236d",
            "file_size": 20480,
            "created_at": "2025-05-22T19:41:37.740861+00:00"
        },
        {
            "bundle_name": "Vodafone_fj",
            "sha1": "1ac5e0dd90b4d92929ea47d7d7013ea040332649",
            "file_size": 20480,
            "created_at": "2025-05-22T19:41:37.743222+00:00"
        },
        {
            "bundle_name": "Orange_li",
            "sha1": "d79f1f3e3064dbdef23ee18ede4bd46cc6d5bf97",
            "file_size": 30720,
            "created_at": "2025-05-22T19:41:37.746319+00:00"
        },
        {
            "bundle_name": "TMobile_at",
            "sha1": "71217f71d34748e0314956baea22f4d66f47e467",
            "file_size": 40960,
            "created_at": "2025-05-22T19:41:37.750649+00:00"
        },
        {
            "bundle_name": "AVEA_tr",
            "sha1": "b24e1ccf2054b6051aedf649f28234193fa317fb",
            "file_size": 20480,
            "created_at": "2025-05-22T19:41:37.753209+00:00"
        },
        {
            "bundle_name": "APT_tw",
            "sha1": "ff052fcbe2ae723231c26209924f49f25b3a244e",
            "file_size": 20480,
            "created_at": "2025-05-22T19:41:37.756239+00:00"
        },
        {
            "bundle_name": "Vodafone_au",
            "sha1": "7c4d893f54e522b35cdd89daa0b44dfc0ebff651",
            "file_size": 30720,
            "created_at": "2025-05-22T19:41:37.761477+00:00"
        },
        {
            "bundle_name": "Unitel_la",
            "sha1": "0f0d77d41d0e34aaaeb521f780498f84d388ac07",
            "file_size": 20480,
            "created_at": "2025-05-22T19:41:37.764087+00:00"
        },
        {
            "bundle_name": "Vodafone_tr",
            "sha1": "93b57822301e6655f61abf5c96db87528bd769d6",
            "file_size": 30720,
            "created_at": "2025-05-22T19:41:37.767663+00:00"
        },
        {
            "bundle_name": "Telenor_se",
            "sha1": "510aa40ae4f0733bd499466005cc9b64729a4acd",
            "file_size": 20480,
            "created_at": "2025-05-22T19:41:37.771008+00:00"
        },
        {
            "bundle_name": "Telstra_au",
            "sha1": "2240b91b3822325e7303a5588337551c62f3a090",
            "file_size": 30720,
            "created_at": "2025-05-22T19:41:37.774509+00:00"
        },
        {
            "bundle_name": "GigSky_US",
            "sha1": "86fa4a5c0a67aaf8b95aa90779676ab975471fad",
            "file_size": 30720,
            "created_at": "2025-05-22T19:41:37.776050+00:00"
        },
        {
            "bundle_name": "Ufone_pk",
            "sha1": "c20f9de9470bedcd52a0b4744eb3f6da4306112c",
            "file_size": 20480,
            "created_at": "2025-05-22T19:41:37.777613+00:00"
        },
        {
            "bundle_name": "Unicom_cn",
            "sha1": "f70658fd91291bcddda11bb8fca8026fe2369cd8",
            "file_size": 30720,
            "created_at": "2025-05-22T19:41:37.779593+00:00"
        },
        {
            "bundle_name": "Bouygues_fr",
            "sha1": "222474f75a1a65ccbd443683d402b2e063533b19",
            "file_size": 30720,
            "created_at": "2025-05-22T19:41:37.781415+00:00"
        },
        {
            "bundle_name": "Dialog_lk",
            "sha1": "277084568b37fe9faf23c24b20c058bf2664ddfb",
            "file_size": 20480,
            "created_at": "2025-05-22T19:41:37.782526+00:00"
        },
        {
            "bundle_name": "TDC_dk",
            "sha1": "d6361994493f32b84799fc641e024d027bf34b19",
            "file_size": 20480,
            "created_at": "2025-05-22T19:41:37.783594+00:00"
        },
        {
            "bundle_name": "Chariton_LTE_US",
            "sha1": "8e34808a1af69d17a9bcc837c224e2db7ccd0399",
            "file_size": 40960,
            "created_at": "2025-05-22T19:41:37.785963+00:00"
        },
        {
            "bundle_name": "Orange_France",
            "sha1": "b62e8906e648da5ad66fbca6aa3be80190e252dc",
            "file_size": 30720,
            "created_at": "2025-05-22T19:41:37.787576+00:00"
        },
        {
            "bundle_name": "Viaero_US",
            "sha1": "6aeeae4c2002443f8f6dd1fd12ae02ea88a2fcb8",
            "file_size": 20480,
            "created_at": "2025-05-22T19:41:37.788662+00:00"
        },
        {
            "bundle_name": "Orange_nl",
            "sha1": "b858cb70286ce4b1b779b89e5e595f616aad473e",
            "file_size": 40960,
            "created_at": "2025-05-22T19:41:37.790768+00:00"
        },
        {
            "bundle_name": "Bell_ca",
            "sha1": "02062da3228476540c83c38d297b80b1acf63fd9",
            "file_size": 40960,
            "created_at": "2025-05-22T19:41:37.792847+00:00"
        },
        {
            "bundle_name": "Vodafone_hu",
            "sha1": "653992c5f433b19eadb29de68a2f4e181d13b705",
            "file_size": 20480,
            "created_at": "2025-05-22T19:41:37.793962+00:00"
        },
        {
            "bundle_name": "SFR_re",
            "sha1": "ce3de93dc170a96c0b60b9184cc3fc177e09c793",
            "file_size": 20480,
            "created_at": "2025-05-22T19:41:37.795310+00:00"
        },
        {
            "bundle_name": "BSNL_in",
            "sha1": "7546d015943ff8ebd9f731f78ae1f8a7f566c980",
            "file_size": 20480,
            "created_at": "2025-05-22T19:41:37.796891+00:00"
        },
        {
            "bundle_name": "O2_sk",
            "sha1": "17adb4fc70eecf49fae83970baff6f53521918b9",
            "file_size": 20480,
            "created_at": "2025-05-22T19:41:37.798187+00:00"
        },
        {
            "bundle_name": "Default",
            "sha1": "7c3a4a8d6c63ef8025ae6f3e78784d5c0b781c71",
            "file_size": 1443840,
            "created_at": "2025-05-22T19:41:37.902123+00:00"
        },
        {
            "bundle_name": "Chat_LTE_US",
            "sha1": "955112f0dfae6d80cbf9f4bf457fc5c8e763d909",
            "file_size": 40960,
            "created_at": "2025-05-22T19:41:37.904655+00:00"
        },
        {
            "bundle_name": "IllinoisValley_LTE_US",
            "sha1": "fe5c045dc272e87a9126374683bc378158dcb7ab",
            "file_size": 40960,
            "created_at": "2025-05-22T19:41:37.907258+00:00"
        },
        {
            "bundle_name": "RoamMobility_uk",
            "sha1": "cd39c62b5cac89e1e29d71b9f32d4621bb8e8a3e",
            "file_size": 20480,
            "created_at": "2025-05-22T19:41:37.908374+00:00"
        },
        {
            "bundle_name": "ChinaTelecom_USIM_cn",
            "sha1": "ce5d110786b95141773a6be7f73a88d68e16149f",
            "file_size": 40960,
            "created_at": "2025-05-22T19:41:37.910449+00:00"
        },
        {
            "bundle_name": "Qtel_mm",
            "sha1": "ce15da8a3b4a2fb8bced0b0b386b83e7677b51e7",
            "file_size": 20480,
            "created_at": "2025-05-22T19:41:37.911551+00:00"
        },
        {
            "bundle_name": "Maxis_my",
            "sha1": "e7b650f71bc3e653f75b789648b1810e43671376",
            "file_size": 30720,
            "created_at": "2025-05-22T19:41:37.913378+00:00"
        },
        {
            "bundle_name": "CarolinaWest_LTE_US",
            "sha1": "e6e3eefa51b80588b0af8fffda89debf2f32213d",
            "file_size": 40960,
            "created_at": "2025-05-22T19:41:37.915842+00:00"
        },
        {
            "bundle_name": "MobileOne_sg",
            "sha1": "792bcbebfb57fe5eb08f9a0555664f2742eaf568",
            "file_size": 20480,
            "created_at": "2025-05-22T19:41:37.917178+00:00"
        },
        {
            "bundle_name": "Pelephone_il",
            "sha1": "7c079a2dd1a946fbafb5e57782f6ad14bbc26db4",
            "file_size": 20480,
            "created_at": "2025-05-22T19:41:37.918467+00:00"
        },
        {
            "bundle_name": "TrueH_th",
            "sha1": "cfb1ed49364e6df6eff39740e3ec9edd254383b8",
            "file_size": 30720,
            "created_at": "2025-05-22T19:41:37.920250+00:00"
        },
        {
            "bundle_name": "NexTech_LTE_US",
            "sha1": "09a8d9aff4ef6f7df2b982af1ac268ec4a026116",
            "file_size": 30720,
            "created_at": "2025-05-22T19:41:37.922314+00:00"
        },
        {
            "bundle_name": "Optimus_pt",
            "sha1": "b7835d6b371ad30eb59900930a4cefcb458c4f5d",
            "file_size": 20480,
            "created_at": "2025-05-22T19:41:37.923407+00:00"
        },
        {
            "bundle_name": "Qtel_qa",
            "sha1": "7167d326d5316d21dccf79e40d4f6cfa46162425",
            "file_size": 20480,
            "created_at": "2025-05-22T19:41:37.924521+00:00"
        },
        {
            "bundle_name": "Bluegrass_LTE_US",
            "sha1": "21a6ab863751512d251f321497841fd9fdd92ee2",
            "file_size": 30720,
            "created_at": "2025-05-22T19:41:37.926571+00:00"
        },
        {
            "bundle_name": "Telenor_no",
            "sha1": "a12defd42f34a7dce58ebc9ab712ff69f751608b",
            "file_size": 30720,
            "created_at": "2025-05-22T19:41:37.928335+00:00"
        },
        {
            "bundle_name": "TMN_pt",
            "sha1": "dc331f7794b2be6f8e076a4bbce973b59fb383c8",
            "file_size": 20480,
            "created_at": "2025-05-22T19:41:37.929462+00:00"
        },
        {
            "bundle_name": "movistar_pe",
            "sha1": "358cb1d148a7242113d8e9a4281e0297d03491c5",
            "file_size": 20480,
            "created_at": "2025-05-22T19:41:37.930774+00:00"
        },
        {
            "bundle_name": "movistar_ec",
            "sha1": "3a7136ee32674c9eb878729f739b65e993101c47",
            "file_size": 30720,
            "created_at": "2025-05-22T19:41:37.932294+00:00"
        },
        {
            "bundle_name": "Hutchison_uk",
            "sha1": "4a7933da57652b5078a535fef80a71f1bc7e5efa",
            "file_size": 30720,
            "created_at": "2025-05-22T19:41:37.934539+00:00"
        },
        {
            "bundle_name": "ChinaTelecom_cn",
            "sha1": "caf072b137c52a9b4efea502b6d6a0744b0115c2",
            "file_size": 30720,
            "created_at": "2025-05-22T19:41:37.937195+00:00"
        },
        {
            "bundle_name": "O2_Germany",
            "sha1": "832fc1c96f0dbf3525503c46bef5b0477486f4e1",
            "file_size": 30720,
            "created_at": "2025-05-22T19:41:37.939871+00:00"
        },
        {
            "bundle_name": "KTF_kr",
            "sha1": "09b9b2ca06decda8cd74f5ae902ea9477b8d6382",
            "file_size": 40960,
            "created_at": "2025-05-22T19:41:37.943332+00:00"
        },
        {
            "bundle_name": "ATT_KORE_US",
            "sha1": "148e659f21f7c7f4f936b12a206e8b6324801486",
            "file_size": 30720,
            "created_at": "2025-05-22T19:41:37.946622+00:00"
        },
        {
            "bundle_name": "Comviq_se",
            "sha1": "5ffd835f8cafc932125a6bebc69a4a8365d3bdde",
            "file_size": 30720,
            "created_at": "2025-05-22T19:41:37.950205+00:00"
        },
        {
            "bundle_name": "Vodafone_Cambio_uk",
            "sha1": "f89c249afdaf540f2d699dddf0f53f7f7bcff608",
            "file_size": 30720,
            "created_at": "2025-05-22T19:41:37.953974+00:00"
        },
        {
            "bundle_name": "WCW_US",
            "sha1": "52d8f70add97943a827465bf312ac89a4bc6cc75",
            "file_size": 20480,
            "created_at": "2025-05-22T19:41:37.955726+00:00"
        },
        {
            "bundle_name": "TMobile_Vodafone_US",
            "sha1": "66af7bca2ee2afe211aac8d7096b5b53cfda431e",
            "file_size": 30720,
            "created_at": "2025-05-22T19:41:37.958520+00:00"
        },
        {
            "bundle_name": "Sprint_ISIM_LTE_US",
            "sha1": "ab594470ded31926b3870a9f5c2dd141c8c2c8b2",
            "file_size": 40960,
            "created_at": "2025-05-22T19:41:37.962852+00:00"
        },
        {
            "bundle_name": "O2_UK",
            "sha1": "44d3859f780a11e36e490f94cd83845e0acc34e5",
            "file_size": 30720,
            "created_at": "2025-05-22T19:41:37.967047+00:00"
        },
        {
            "bundle_name": "TMobile_hu",
            "sha1": "d6c75572949fda25276db61f362273897089c1ab",
            "file_size": 30720,
            "created_at": "2025-05-22T19:41:37.972275+00:00"
        },
        {
            "bundle_name": "Vodafone_ro",
            "sha1": "3ab6a07de78780e0af2440b3f6ee278509b767e3",
            "file_size": 30720,
            "created_at": "2025-05-22T19:41:37.976029+00:00"
        },
        {
            "bundle_name": "Sonera_fi",
            "sha1": "48aadfc45ab07c7232928b6725f2ca97f3f4bcd6",
            "file_size": 20480,
            "created_at": "2025-05-22T19:41:37.977788+00:00"
        },
        {
            "bundle_name": "Appalachian_LTE_US",
            "sha1": "99a0335143f628dd2e8af15bf3a1733a97d0ac63",
            "file_size": 40960,
            "created_at": "2025-05-22T19:41:37.980295+00:00"
        },
        {
            "bundle_name": "OPT_nc",
            "sha1": "919df283d35d8505739aba9e83e5d0e22e372016",
            "file_size": 20480,
            "created_at": "2025-05-22T19:41:37.981458+00:00"
        },
        {
            "bundle_name": "ATT_US",
            "sha1": "8549d76796ee284dfde7e81cfd24ff0cad5266e8",
            "file_size": 235520,
            "created_at": "2025-05-22T19:41:37.997696+00:00"
        },
        {
            "bundle_name": "Telus_Koodo_ca",
            "sha1": "942520ef6cc2b54dd10bb2eccac4053578629c2c",
            "file_size": 40960,
            "created_at": "2025-05-22T19:41:37.999854+00:00"
        },
        {
            "bundle_name": "Telenor_hu",
            "sha1": "d11e41d90ea3d151fa53f21e2bd258babde31d67",
            "file_size": 20480,
            "created_at": "2025-05-22T19:41:38.001012+00:00"
        },
        {
            "bundle_name": "PTCI_LTE_US",
            "sha1": "79214209681ebdcedab44794bd6ba6138c033adf",
            "file_size": 30720,
            "created_at": "2025-05-22T19:41:38.002978+00:00"
        },
        {
            "bundle_name": "StrataNetwork_LTE_US",
            "sha1": "281298f5863d802faf55a2e3271eb9bb3267cbfe",
            "file_size": 40960,
            "created_at": "2025-05-22T19:41:38.005107+00:00"
        },
        {
            "bundle_name": "Vodafone_uk",
            "sha1": "57d6048941d1a658a0c07cca748baccab1a99432",
            "file_size": 20480,
            "created_at": "2025-05-22T19:41:38.006489+00:00"
        },
        {
            "bundle_name": "Vodafone_ie",
            "sha1": "dde76dba03df116dfdfa2581d5ac62c64e756279",
            "file_size": 30720,
            "created_at": "2025-05-22T19:41:38.008060+00:00"
        },
        {
            "bundle_name": "Telia_dk",
            "sha1": "195003d05395d9b8020b0f9c7993bff999495fa8",
            "file_size": 20480,
            "created_at": "2025-05-22T19:41:38.009420+00:00"
        },
        {
            "bundle_name": "Globe_ph",
            "sha1": "e1c00170d95d771da9e349b89065297a4562e04c",
            "file_size": 30720,
            "created_at": "2025-05-22T19:41:38.011204+00:00"
        },
        {
            "bundle_name": "Hutchison_it",
            "sha1": "44508c12f4de6acf27ffac60bd89b4a91afae76d",
            "file_size": 30720,
            "created_at": "2025-05-22T19:41:38.012974+00:00"
        },
        {
            "bundle_name": "Viva_kw",
            "sha1": "b36277de3f7ee80bd837adbe9e9779e08b1a540c",
            "file_size": 20480,
            "created_at": "2025-05-22T19:41:38.014075+00:00"
        },
        {
            "bundle_name": "RoamMobility_ca",
            "sha1": "039cd33d5d1778fd94b4b59b19d0cae72321155b",
            "file_size": 20480,
            "created_at": "2025-05-22T19:41:38.015145+00:00"
        },
        {
            "bundle_name": "PioneerCellular_LTE_US",
            "sha1": "84e6c086f5e494099fed4160284db909aebb8f96",
            "file_size": 30720,
            "created_at": "2025-05-22T19:41:38.017200+00:00"
        },
        {
            "bundle_name": "mobilkom_at",
            "sha1": "5581e8eb8750f108555484c3fcd9d8c59812ba20",
            "file_size": 20480,
            "created_at": "2025-05-22T19:41:38.018543+00:00"
        },
        {
            "bundle_name": "Vodafone_za",
            "sha1": "481845af0b600e3fd5a744150027c7a05eda6dab",
            "file_size": 30720,
            "created_at": "2025-05-22T19:41:38.020473+00:00"
        },
        {
            "bundle_name": "movistar_cl",
            "sha1": "00c1ef4fbcf319ba460ac1737c8d5201711c7792",
            "file_size": 30720,
            "created_at": "2025-05-22T19:41:38.022086+00:00"
        },
        {
            "bundle_name": "Telcel_mx",
            "sha1": "4deee03837f4d7e2d50fcfb499bd571e70583943",
            "file_size": 30720,
            "created_at": "2025-05-22T19:41:38.023873+00:00"
        },
        {
            "bundle_name": "O2_cz",
            "sha1": "6a794f49ffb7d29026b837ae955e81138d3416ae",
            "file_size": 20480,
            "created_at": "2025-05-22T19:41:38.024958+00:00"
        },
        {
            "bundle_name": "Hutchison_Wind_it",
            "sha1": "d1c71f9babaf19a4499dd83d0dc245ad53a523ff",
            "file_size": 20480,
            "created_at": "2025-05-22T19:41:38.026081+00:00"
        },
        {
            "bundle_name": "MobiCom_mn",
            "sha1": "f6332f8355dd501be47f8715fedb9f4db0ec41f0",
            "file_size": 20480,
            "created_at": "2025-05-22T19:41:38.027167+00:00"
        },
        {
            "bundle_name": "THC_LTE_US",
            "sha1": "d9c973c7cf0d9ddc8da3aac605d2f7310f3a52bc",
            "file_size": 40960,
            "created_at": "2025-05-22T19:41:38.029722+00:00"
        },
        {
            "bundle_name": "Viva_bh",
            "sha1": "f72aa085c081c3f0fafc3aac6d6dfcc0bc0c3905",
            "file_size": 20480,
            "created_at": "2025-05-22T19:41:38.030866+00:00"
        },
        {
            "bundle_name": "Claro_pa",
            "sha1": "974dce8d5c3353e4d23ce7454f5071103d05d568",
            "file_size": 20480,
            "created_at": "2025-05-22T19:41:38.032222+00:00"
        },
        {
            "bundle_name": "One_at",
            "sha1": "bb92cec888f799161fb43bae150ac3c62d7c9517",
            "file_size": 30720,
            "created_at": "2025-05-22T19:41:38.034433+00:00"
        },
        {
            "bundle_name": "LuxGSM_lu",
            "sha1": "d9a0db6184bd6c93a2ec58655b88a0cbf483d78d",
            "file_size": 30720,
            "created_at": "2025-05-22T19:41:38.037501+00:00"
        },
        {
            "bundle_name": "Qtel_mv",
            "sha1": "dcd48a63e847e8ca9da7d4f89ccd49c01be65d51",
            "file_size": 20480,
            "created_at": "2025-05-22T19:41:38.039639+00:00"
        },
        {
            "bundle_name": "RelianceJio_in",
            "sha1": "89756ec33834b7471b1f8a86a85c6b6d1dec7e18",
            "file_size": 40960,
            "created_at": "2025-05-22T19:41:38.060901+00:00"
        },
        {
            "bundle_name": "Telkomsel_id",
            "sha1": "6902aa25af344cea4ec52adde924612976ed9c1d",
            "file_size": 20480,
            "created_at": "2025-05-22T19:41:38.063920+00:00"
        },
        {
            "bundle_name": "Hutchison_at",
            "sha1": "758dd5d7763e87f4a4eb580e275ca2d8d5ffe6a0",
            "file_size": 30720,
            "created_at": "2025-05-22T19:41:38.067667+00:00"
        },
        {
            "bundle_name": "USCellular_LTE_US",
            "sha1": "413765c4a9ad93c8db119ef612b4ff9f937f4ea4",
            "file_size": 40960,
            "created_at": "2025-05-22T19:41:38.071280+00:00"
        },
        {
            "bundle_name": "CSL_hk",
            "sha1": "53bc3706d8f004c0cd65e9daeb142f3c0e894eeb",
            "file_size": 40960,
            "created_at": "2025-05-22T19:41:38.074176+00:00"
        },
        {
            "bundle_name": "Docomo_jp",
            "sha1": "bd2243195c52c27326cb3a1a03fac17acaa97d57",
            "file_size": 40960,
            "created_at": "2025-05-22T19:41:38.076613+00:00"
        },
        {
            "bundle_name": "SFR_fr",
            "sha1": "29da11bd19c86d793ba06247ddc549e8be5c15f3",
            "file_size": 30720,
            "created_at": "2025-05-22T19:41:38.078715+00:00"
        },
        {
            "bundle_name": "SmarTone_mo",
            "sha1": "f81a7cf42ea758a4b664bb9cb52343b2481b50cd",
            "file_size": 30720,
            "created_at": "2025-05-22T19:41:38.080319+00:00"
        },
        {
            "bundle_name": "Vodafone_de",
            "sha1": "f2c2a481bb67d20c5d1d45e60b7f0e716a87780d",
            "file_size": 30720,
            "created_at": "2025-05-22T19:41:38.082195+00:00"
        },
        {
            "bundle_name": "Inland_LTE_US",
            "sha1": "6426378bc921dd83d2f42ee0b540f85dc3156f77",
            "file_size": 30720,
            "created_at": "2025-05-22T19:41:38.084230+00:00"
        },
        {
            "bundle_name": "Chunghwa_tw",
            "sha1": "8823887cac48ce51d504b3198e6f1b241ecbac30",
            "file_size": 30720,
            "created_at": "2025-05-22T19:41:38.086100+00:00"
        },
        {
            "bundle_name": "KPN_nl",
            "sha1": "af1d0db524fa9b6c23be13d45f91af84bca418ea",
            "file_size": 30720,
            "created_at": "2025-05-22T19:41:38.087933+00:00"
        },
        {
            "bundle_name": "Verizon_LTE_US",
            "sha1": "1aee22ff2f8ef919b02d9f62188935c83ee48bbb",
            "file_size": 51200,
            "created_at": "2025-05-22T19:41:38.090738+00:00"
        },
        {
            "bundle_name": "TMobile_gr",
            "sha1": "c3edede51fcacf12a3722930696f1d5083dd33b3",
            "file_size": 40960,
            "created_at": "2025-05-22T19:41:38.093151+00:00"
        },
        {
            "bundle_name": "Yoigo_Pepephone_es",
            "sha1": "762dea2b319f037d59c49962c460922ae0952de5",
            "file_size": 20480,
            "created_at": "2025-05-22T19:41:38.094334+00:00"
        },
        {
            "bundle_name": "Orange_re",
            "sha1": "98f7762f10464977d2389defb63ba8b5dc202f30",
            "file_size": 20480,
            "created_at": "2025-05-22T19:41:38.095447+00:00"
        },
        {
            "bundle_name": "XL_id",
            "sha1": "55b40e3ce7941a21d7be59e8be47ab8c0da4146c",
            "file_size": 20480,
            "created_at": "2025-05-22T19:41:38.096792+00:00"
        },
        {
            "bundle_name": "VimpelCom_ru",
            "sha1": "b67fc80bbed059ead4553922ba42deebfd2cf70a",
            "file_size": 30720,
            "created_at": "2025-05-22T19:41:38.098790+00:00"
        },
        {
            "bundle_name": "O2_Sky_uk",
            "sha1": "3533c77b5baefdc8c445f2d263e88c7d493d096a",
            "file_size": 20480,
            "created_at": "2025-05-22T19:41:38.099895+00:00"
        },
        {
            "bundle_name": "Orange_ch",
            "sha1": "89eedd03e3f9231aa8f4a99daae6b1a53d5c57b7",
            "file_size": 30720,
            "created_at": "2025-05-22T19:41:38.101492+00:00"
        },
        {
            "bundle_name": "Truphone_US",
            "sha1": "c9ace36cef9d4db9ccdab1cf8ee498e4c6774ebf",
            "file_size": 20480,
            "created_at": "2025-05-22T19:41:38.102618+00:00"
        },
        {
            "bundle_name": "Cellcom_LTE_US",
            "sha1": "931b5ebc94678593e86d24fe3ca40fd78846657c",
            "file_size": 40960,
            "created_at": "2025-05-22T19:41:38.104872+00:00"
        },
        {
            "bundle_name": "Turkcell_tr",
            "sha1": "39cc02a97f2542cc3c6459196c65e410a8032127",
            "file_size": 20480,
            "created_at": "2025-05-22T19:41:38.105964+00:00"
        },
        {
            "bundle_name": "Zain_kw",
            "sha1": "616f4831e49b327d4c616a187c9964cb4277e5c8",
            "file_size": 30720,
            "created_at": "2025-05-22T19:41:38.107800+00:00"
        },
        {
            "bundle_name": "Bootstrap_ATT_US",
            "sha1": "b8a4d823dff7d25782752db7ece1e2b66ecfe0c5",
            "file_size": 20480,
            "created_at": "2025-05-22T19:41:38.108941+00:00"
        },
        {
            "bundle_name": "OQCFactoryMultimode",
            "sha1": "a30bd0f62120b1cb4caf2599c0ac277513c5580e",
            "file_size": 30720,
            "created_at": "2025-05-22T19:41:38.111484+00:00"
        },
        {
            "bundle_name": "AIS_th",
            "sha1": "b8f1c0d685edbb91e66289a9fad03142d92ac334",
            "file_size": 40960,
            "created_at": "2025-05-22T19:41:38.113630+00:00"
        },
        {
            "bundle_name": "Verizon_Charter_LTE_US",
            "sha1": "15b23733f71d27cdda7b5535c20a2ba3096fb4df",
            "file_size": 61440,
            "created_at": "2025-05-22T19:41:38.116652+00:00"
        },
        {
            "bundle_name": "Mirs_il",
            "sha1": "116b27ca8f0e6f0d5a58b8c8209fc00a8bba2df4",
            "file_size": 20480,
            "created_at": "2025-05-22T19:41:38.117985+00:00"
        },
        {
            "bundle_name": "iusacell_Unefon_mx",
            "sha1": "69ee0b5b61b97b1d6fc07090b854ba1052b536e7",
            "file_size": 20480,
            "created_at": "2025-05-22T19:41:38.119068+00:00"
        },
        {
            "bundle_name": "movistar_pa",
            "sha1": "9a0d9a4a976bad862fe1d0c87d14dd5647c9ada5",
            "file_size": 20480,
            "created_at": "2025-05-22T19:41:38.120403+00:00"
        },
        {
            "bundle_name": "movistar_mx",
            "sha1": "2733d8bc31b66c47c8430379407cf86b937c554b",
            "file_size": 20480,
            "created_at": "2025-05-22T19:41:38.121708+00:00"
        },
        {
            "bundle_name": "Hutchison_dk",
            "sha1": "c9156f54c8ed578178b846666a53882ddd427bfb",
            "file_size": 30720,
            "created_at": "2025-05-22T19:41:38.123516+00:00"
        },
        {
            "bundle_name": "TMobile_nl",
            "sha1": "a9b88d1880ddcb2490a3d49d03a03a851b1945e6",
            "file_size": 40960,
            "created_at": "2025-05-22T19:41:38.125554+00:00"
        },
        {
            "bundle_name": "Cellcom_il",
            "sha1": "a32a96e851905cdda8fb178eeaec40ffca60e6ca",
            "file_size": 20480,
            "created_at": "2025-05-22T19:41:38.126902+00:00"
        },
        {
            "bundle_name": "Sunrise_ch",
            "sha1": "ba7c7964b8db6d1a05f36b910d17ec08f0e7bc22",
            "file_size": 20480,
            "created_at": "2025-05-22T19:41:38.128178+00:00"
        },
        {
            "bundle_name": "Vodafone_gr",
            "sha1": "0f2c805833e537d819fc16a0bf9edbfcd421f212",
            "file_size": 30720,
            "created_at": "2025-05-22T19:41:38.129787+00:00"
        },
        {
            "bundle_name": "Comcel_co",
            "sha1": "c6e7c3e3722f73936b614218fcde611a33a6fd9e",
            "file_size": 30720,
            "created_at": "2025-05-22T19:41:38.131337+00:00"
        },
        {
            "bundle_name": "Claro_br",
            "sha1": "e22c00781de86f74f0e4ab21f08f90328e78d692",
            "file_size": 30720,
            "created_at": "2025-05-22T19:41:38.133114+00:00"
        },
        {
            "bundle_name": "Choice_gu",
            "sha1": "2d579eb9f7715551bf8da77ee0ba58f6676a126e",
            "file_size": 30720,
            "created_at": "2025-05-22T19:41:38.136698+00:00"
        },
        {
            "bundle_name": "Telefonica_es",
            "sha1": "638df70dfcbc41bfff6ca471ff70e0aabba63f7e",
            "file_size": 20480,
            "created_at": "2025-05-22T19:41:38.139341+00:00"
        },
        {
            "bundle_name": "Reliance_RCOM_in",
            "sha1": "226396cef3fa1cfff47963373220129a25793a7c",
            "file_size": 20480,
            "created_at": "2025-05-22T19:41:38.142093+00:00"
        },
        {
            "bundle_name": "NetCom_no",
            "sha1": "78785cf6a6c967ac3ad91388ba2d8b16ec23124d",
            "file_size": 20480,
            "created_at": "2025-05-22T19:41:38.144467+00:00"
        },
        {
            "bundle_name": "Hutchison_mo",
            "sha1": "06158141785f19acc0872d2eab7c24ab5316f690",
            "file_size": 20480,
            "created_at": "2025-05-22T19:41:38.146738+00:00"
        },
        {
            "bundle_name": "OQCFactoryUMTS",
            "sha1": "603f60a08f05679c305e1ba59b7d2883b6958aab",
            "file_size": 30720,
            "created_at": "2025-05-22T19:41:38.150700+00:00"
        },
        {
            "bundle_name": "Warid_pk",
            "sha1": "a370bb2093afca298fe7dffb72460a5ecc6cced7",
            "file_size": 20480,
            "created_at": "2025-05-22T19:41:38.153557+00:00"
        },
        {
            "bundle_name": "PCCW_hk",
            "sha1": "bd92f0e5f49c2de009c7f0f9d71b8f05c9609bbd",
            "file_size": 40960,
            "created_at": "2025-05-22T19:41:38.158015+00:00"
        },
        {
            "bundle_name": "Telecom_nz",
            "sha1": "500475ad382ddeeb38599d203fbb5c68f5e7a34e",
            "file_size": 20480,
            "created_at": "2025-05-22T19:41:38.160719+00:00"
        },
        {
            "bundle_name": "TDC_se",
            "sha1": "72d0c7e0df8e659a658891a315edfe6cb7925b6c",
            "file_size": 20480,
            "created_at": "2025-05-22T19:41:38.163410+00:00"
        },
        {
            "bundle_name": "AppWire_LTE_US",
            "sha1": "ec64068083a315e35644d8407b672d40ba3ca5f3",
            "file_size": 30720,
            "created_at": "2025-05-22T19:41:38.167983+00:00"
        },
        {
            "bundle_name": "SingTel_sg",
            "sha1": "53b2af27aa705fa03f58c85fbf6357cde4ba8fcc",
            "file_size": 40960,
            "created_at": "2025-05-22T19:41:38.172010+00:00"
        },
        {
            "bundle_name": "NWM_LTE_US",
            "sha1": "9cab0d903a3791d231c5ff2af21e1d355c0d0a5e",
            "file_size": 40960,
            "created_at": "2025-05-22T19:41:38.175362+00:00"
        },
        {
            "bundle_name": "Laotel_la",
            "sha1": "7b91b2941ed4fcf94daeec1fbe4d0adaf093906c",
            "file_size": 20480,
            "created_at": "2025-05-22T19:41:38.177017+00:00"
        },
        {
            "bundle_name": "Porta_ec",
            "sha1": "91dd5c1ec356d047dcdd5e4fddbe41f6f4fc3b3a",
            "file_size": 20480,
            "created_at": "2025-05-22T19:41:38.178577+00:00"
        },
        {
            "bundle_name": "Tele2_se",
            "sha1": "f7dd50b220fbbbb8050c06ab64502ba09cc25fe9",
            "file_size": 30720,
            "created_at": "2025-05-22T19:41:38.180164+00:00"
        },
        {
            "bundle_name": "Swisscom_ch",
            "sha1": "b8186dcd3448f55c213a86d35be51e38af77c12d",
            "file_size": 20480,
            "created_at": "2025-05-22T19:41:38.181595+00:00"
        },
        {
            "bundle_name": "Grameenphone_bd",
            "sha1": "032aa3e6b64ff966e7110fe2d299a9fdb5e30685",
            "file_size": 20480,
            "created_at": "2025-05-22T19:41:38.182700+00:00"
        },
        {
            "bundle_name": "mobilkom_bg",
            "sha1": "9ea9ce3bf11da5e84d71bfba3aeb70bd94dc93bb",
            "file_size": 20480,
            "created_at": "2025-05-22T19:41:38.183757+00:00"
        },
        {
            "bundle_name": "Dhiraagu_mv",
            "sha1": "415206eb99bcaf529a778d864b2bf47b3aa8c576",
            "file_size": 30720,
            "created_at": "2025-05-22T19:41:38.185311+00:00"
        },
        {
            "bundle_name": "Telus_ca",
            "sha1": "efb2d589ddf7cc64ffaf44dbeba3be7fb8536582",
            "file_size": 40960,
            "created_at": "2025-05-22T19:41:38.187368+00:00"
        },
        {
            "bundle_name": "Panhandle_US",
            "sha1": "c79cbe390ef0b4be02e16f1001f4a891e5e30e50",
            "file_size": 20480,
            "created_at": "2025-05-22T19:41:38.188458+00:00"
        },
        {
            "bundle_name": "CellularSouth_LTE_US",
            "sha1": "da8afaf8754f1a84028064917f2ab782df1d7ea2",
            "file_size": 40960,
            "created_at": "2025-05-22T19:41:38.191063+00:00"
        },
        {
            "bundle_name": "Vodafone_nl",
            "sha1": "b8801804f6481f2b49f0d4d0c5a42c63cb9d5a89",
            "file_size": 20480,
            "created_at": "2025-05-22T19:41:38.192150+00:00"
        },
        {
            "bundle_name": "VOX_lu",
            "sha1": "1869be9d6dcedb5cd38f183c748120474c1bf8ff",
            "file_size": 30720,
            "created_at": "2025-05-22T19:41:38.193701+00:00"
        },
        {
            "bundle_name": "TMobile_pl",
            "sha1": "ac7526c70edd64ff22ec1d44261ce7d5bb34544e",
            "file_size": 30720,
            "created_at": "2025-05-22T19:41:38.195494+00:00"
        },
        {
            "bundle_name": "GTA_gu",
            "sha1": "37fb4832a3e2300d4c4f0aa03a1f9edb5d232041",
            "file_size": 20480,
            "created_at": "2025-05-22T19:41:38.196802+00:00"
        },
        {
            "bundle_name": "Zain_sa",
            "sha1": "dfbb96a96d13b5a29ab6baea4990e1117a552177",
            "file_size": 20480,
            "created_at": "2025-05-22T19:41:38.206805+00:00"
        },
        {
            "bundle_name": "TMobile_uk",
            "sha1": "47f8ade7bc988e6610a3a342e87a65667b6456a8",
            "file_size": 40960,
            "created_at": "2025-05-22T19:41:38.208897+00:00"
        },
        {
            "bundle_name": "Strata_LTE_US",
            "sha1": "b613df55d2a19bb83d280e83082f8511e02dc1d9",
            "file_size": 40960,
            "created_at": "2025-05-22T19:41:38.211226+00:00"
        },
        {
            "bundle_name": "Oi_br",
            "sha1": "01e25f56c167dc39013bba13edf29b43850c42f2",
            "file_size": 20480,
            "created_at": "2025-05-22T19:41:38.212535+00:00"
        },
        {
            "bundle_name": "movistar_co",
            "sha1": "f091c84484795b42df9ed9213ba70d99233c2b95",
            "file_size": 20480,
            "created_at": "2025-05-22T19:41:38.213617+00:00"
        },
        {
            "bundle_name": "Hutchison_ie",
            "sha1": "4e99e40ce113609196e8a9786374a90fc354a384",
            "file_size": 30720,
            "created_at": "2025-05-22T19:41:38.215416+00:00"
        },
        {
            "bundle_name": "CarrierLab",
            "sha1": "6a69b4141773507e28006d82d1b6269bd6229f29",
            "file_size": 30720,
            "created_at": "2025-05-22T19:41:38.217183+00:00"
        },
        {
            "bundle_name": "Etisalat_ae",
            "sha1": "c6d18598978806e01c5bf9335cf1040c9bb99f17",
            "file_size": 20480,
            "created_at": "2025-05-22T19:41:38.218272+00:00"
        },
        {
            "bundle_name": "Vodafone_cz",
            "sha1": "6b7784f4b37d2485c415e3310b6420aec3c5ce9a",
            "file_size": 30720,
            "created_at": "2025-05-22T19:41:38.219809+00:00"
        },
        {
            "bundle_name": "Hutchison_hk",
            "sha1": "ab0dac03118c600b5ce15f65ed72df220ad81ff7",
            "file_size": 30720,
            "created_at": "2025-05-22T19:41:38.221569+00:00"
        },
        {
            "bundle_name": "EntelPCS_cl",
            "sha1": "ccbff5eb6190e1cd97d79c84fc89901497e2a0e5",
            "file_size": 20480,
            "created_at": "2025-05-22T19:41:38.222887+00:00"
        },
        {
            "bundle_name": "CTM_mo",
            "sha1": "fab4c91c2b60e351df02d85945982c20b2fc53b9",
            "file_size": 30720,
            "created_at": "2025-05-22T19:41:38.224673+00:00"
        },
        {
            "bundle_name": "Celcom_my",
            "sha1": "c00c401a725595529452e9e5415f5c26804353da",
            "file_size": 30720,
            "created_at": "2025-05-22T19:41:38.226375+00:00"
        },
        {
            "bundle_name": "Yoigo_Masmovil_es",
            "sha1": "d5a4e4be364b461b0403705d28725f4be6f55dc9",
            "file_size": 20480,
            "created_at": "2025-05-22T19:41:38.227437+00:00"
        },
        {
            "bundle_name": "Vodafone_it",
            "sha1": "804fe3df900e81a8927ce8cd03d601320efa37ff",
            "file_size": 20480,
            "created_at": "2025-05-22T19:41:38.228494+00:00"
        },
        {
            "bundle_name": "Verizon_Comcast_LTE_US",
            "sha1": "88de83b75261de4d60669d8d43379d3fe4fe418a",
            "file_size": 61440,
            "created_at": "2025-05-22T19:41:38.231483+00:00"
        },
        {
            "bundle_name": "LGU_kr",
            "sha1": "b1f16bd7579f459a9073ece7b46facd3637035d3",
            "file_size": 40960,
            "created_at": "2025-05-22T19:41:38.233622+00:00"
        },
        {
            "bundle_name": "TIM_Italy",
            "sha1": "8ebcc5e42e6fbc1a0a90c6108c2a935cd53ccb68",
            "file_size": 20480,
            "created_at": "2025-05-22T19:41:38.235412+00:00"
        },
        {
            "bundle_name": "DNA_fi",
            "sha1": "30c0285de086cccb5382bba658bb6cac3fcfefc9",
            "file_size": 30720,
            "created_at": "2025-05-22T19:41:38.238495+00:00"
        },
        {
            "bundle_name": "FarEasTone_tw",
            "sha1": "1177d1da1e37b696fe8d9817a46e30ffbcecf7c1",
            "file_size": 40960,
            "created_at": "2025-05-22T19:41:38.245308+00:00"
        },
        {
            "bundle_name": "Smart_kh",
            "sha1": "1fa5bed790f25c5e9ab0f1281b87fa80467416a9",
            "file_size": 20480,
            "created_at": "2025-05-22T19:41:38.247195+00:00"
        },
        {
            "bundle_name": "MegaFon_ru",
            "sha1": "3ceb0bfda906b005bb7e32324f54247970b7c1ea",
            "file_size": 30720,
            "created_at": "2025-05-22T19:41:38.249575+00:00"
        },
        {
            "bundle_name": "CMCC_cn",
            "sha1": "ddc6534092f1598587c65fc9fa5cd903a96abe45",
            "file_size": 30720,
            "created_at": "2025-05-22T19:41:38.252340+00:00"
        },
        {
            "bundle_name": "Rogers_ca",
            "sha1": "e787e1498f917fffe7fb883eee8e8c763affa17e",
            "file_size": 235520,
            "created_at": "2025-05-22T19:41:38.279285+00:00"
        },
        {
            "bundle_name": "Telenet_be",
            "sha1": "bf1fcbec835a8c3204fdf9f5188bb4228defee19",
            "file_size": 20480,
            "created_at": "2025-05-22T19:41:38.280514+00:00"
        },
        {
            "bundle_name": "Docomo_gu",
            "sha1": "0411dab353a34d911b175901622c370d6e92411f",
            "file_size": 20480,
            "created_at": "2025-05-22T19:41:38.281584+00:00"
        },
        {
            "bundle_name": "TDC_no",
            "sha1": "319abd7648a76362e33461c5071013741dadd343",
            "file_size": 30720,
            "created_at": "2025-05-22T19:41:38.283100+00:00"
        },
        {
            "bundle_name": "Viettel_vn",
            "sha1": "62112e05832db27f41ad4ab1c367f314588a549d",
            "file_size": 20480,
            "created_at": "2025-05-22T19:41:38.284097+00:00"
        },
        {
            "bundle_name": "Qtel_kw",
            "sha1": "ccd5da1337141bcefa32443d62be279d9104c3eb",
            "file_size": 20480,
            "created_at": "2025-05-22T19:41:38.285103+00:00"
        },
        {
            "bundle_name": "Optus_au",
            "sha1": "df146ad11cb03fe70b91ef07164b83aa9321d328",
            "file_size": 30720,
            "created_at": "2025-05-22T19:41:38.286783+00:00"
        },
        {
            "bundle_name": "True_th",
            "sha1": "ac9cd5e760301b9e1f9a09d279fc6c555c88f486",
            "file_size": 20480,
            "created_at": "2025-05-22T19:41:38.287810+00:00"
        },
        {
            "bundle_name": "Claro_cl",
            "sha1": "bbc8e9a61363b6a5061bce06de5b5e5aaccc3884",
            "file_size": 20480,
            "created_at": "2025-05-22T19:41:38.289079+00:00"
        },
        {
            "bundle_name": "Bootstrap_EE_UK",
            "sha1": "d00f46f9e739009b545e0237473fb73b4d7f27e0",
            "file_size": 20480,
            "created_at": "2025-05-22T19:41:38.290210+00:00"
        },
        {
            "bundle_name": "Orange_es",
            "sha1": "e9689895f1bb9d76fb84956ba8cdfb41d9a68315",
            "file_size": 30720,
            "created_at": "2025-05-22T19:41:38.291821+00:00"
        },
        {
            "bundle_name": "elisa_fi",
            "sha1": "6f47bfbfbceb3976146cf468bd81c690bf3903d1",
            "file_size": 20480,
            "created_at": "2025-05-22T19:41:38.292937+00:00"
        },
        {
            "bundle_name": "SmarTone_hk",
            "sha1": "e7470d7694ad27434b739cc82a7afbd2626fef6c",
            "file_size": 30720,
            "created_at": "2025-05-22T19:41:38.294553+00:00"
        },
        {
            "bundle_name": "iusacell_mx",
            "sha1": "12fed2b2006fffdc327022b4f6cfa4e875a65e80",
            "file_size": 20480,
            "created_at": "2025-05-22T19:41:38.295673+00:00"
        },
        {
            "bundle_name": "dtac_th",
            "sha1": "70ee3d8da3d412f5f26e9cea81d99b61cc36cd43",
            "file_size": 30720,
            "created_at": "2025-05-22T19:41:38.297926+00:00"
        },
        {
            "bundle_name": "nTelos_LTE_US",
            "sha1": "b4b1270837c9f5463fb374683240210b1539c9a9",
            "file_size": 30720,
            "created_at": "2025-05-22T19:41:38.299768+00:00"
        },
        {
            "bundle_name": "Robi_bd",
            "sha1": "1894b3deee7ebfcfc5ad51f75110f551bff4b0ce",
            "file_size": 20480,
            "created_at": "2025-05-22T19:41:38.300858+00:00"
        },
        {
            "bundle_name": "TMobile_Germany",
            "sha1": "66ef25fc294f847ffc0957534078b9531fc32496",
            "file_size": 40960,
            "created_at": "2025-05-22T19:41:38.302885+00:00"
        },
        {
            "bundle_name": "O2_Prepaid_UK",
            "sha1": "2be684c0fd1c5ab5fa17b79352ac6e3a845608a3",
            "file_size": 30720,
            "created_at": "2025-05-22T19:41:38.304667+00:00"
        },
        {
            "bundle_name": "Vodafone_nz",
            "sha1": "bafb0eccec81597285e357cc030caab8a02be86b",
            "file_size": 20480,
            "created_at": "2025-05-22T19:41:38.305760+00:00"
        },
        {
            "bundle_name": "Nextel_mx",
            "sha1": "dc445c0dca1475d7ce4c6310d7baed7076bf0476",
            "file_size": 20480,
            "created_at": "2025-05-22T19:41:38.306836+00:00"
        },
        {
            "bundle_name": "Hutchison_se",
            "sha1": "b6fe193d1ada4aa26dc3f999e141b8c8af1d9abd",
            "file_size": 30720,
            "created_at": "2025-05-22T19:41:38.308604+00:00"
        },
        {
            "bundle_name": "CMCC_hk",
            "sha1": "e38f197a095a9dae5c5778ad46f2d8cc7cd04d84",
            "file_size": 20480,
            "created_at": "2025-05-22T19:41:38.309806+00:00"
        },
        {
            "bundle_name": "Smart_ph",
            "sha1": "8ca0ed801fb9e82034071abf98b3d020e03b84c4",
            "file_size": 20480,
            "created_at": "2025-05-22T19:41:38.310888+00:00"
        },
        {
            "bundle_name": "Verizon_Response_LTE_US",
            "sha1": "495b00994b2af37ec9de8aaa28644955c5a6976c",
            "file_size": 51200,
            "created_at": "2025-05-22T19:41:38.313650+00:00"
        },
        {
            "bundle_name": "du_ae",
            "sha1": "1d05915a2d2dc19d2603e05ed8b9af43596c655f",
            "file_size": 30720,
            "created_at": "2025-05-22T19:41:38.315454+00:00"
        },
        {
            "bundle_name": "Vodafone_es",
            "sha1": "1386395a0972b1aa4ad7fb1bbeafe678da866fa0",
            "file_size": 30720,
            "created_at": "2025-05-22T19:41:38.316964+00:00"
        },
        {
            "bundle_name": "Robi_BhartiAirtel_bd",
            "sha1": "f8bd5d6f489a71a475fc36c249c39286591fe080",
            "file_size": 20480,
            "created_at": "2025-05-22T19:41:38.318031+00:00"
        },
        {
            "bundle_name": "Proximus_be",
            "sha1": "5c390fb91ca55a71c36fcf33cfc2f3adf22dbd99",
            "file_size": 20480,
            "created_at": "2025-05-22T19:41:38.319091+00:00"
        },
        {
            "bundle_name": "SKT_kr",
            "sha1": "455ddb8ab2cd0c5f2409bd24cdaecb100092f7c9",
            "file_size": 30720,
            "created_at": "2025-05-22T19:41:38.320838+00:00"
        },
        {
            "bundle_name": "Unknown",
            "sha1": "a503aa1bb564ec02fb3bcf90278418d0d7bbf1ed",
            "file_size": 20480,
            "created_at": "2025-05-22T19:41:38.321924+00:00"
        },
        {
            "bundle_name": "du_Virgin_ae",
            "sha1": "a94157f61b4b750905bf876217b6a049ba15ecbc",
            "file_size": 20480,
            "created_at": "2025-05-22T19:41:38.323250+00:00"
        },
        {
            "bundle_name": "TMobile_cz",
            "sha1": "ae44098c2e28b490eef8e4422708b6c84d5bf5a0",
            "file_size": 40960,
            "created_at": "2025-05-22T19:41:38.325263+00:00"
        },
        {
            "bundle_name": "Telia_se",
            "sha1": "3cad777f93dfe236d7f1421d6e55c897ea2e7b3f",
            "file_size": 20480,
            "created_at": "2025-05-22T19:41:38.326568+00:00"
        },
        {
            "bundle_name": "Zain_bh",
            "sha1": "95f9a635bd1f6e6df04c761048de128f4f22a870",
            "file_size": 20480,
            "created_at": "2025-05-22T19:41:38.327622+00:00"
        },
        {
            "bundle_name": "KDDI_LTE_only_jp",
            "sha1": "1d12f18896e1d92386be19dee1b331064eb9c3e5",
            "file_size": 51200,
            "created_at": "2025-05-22T19:41:38.330482+00:00"
        },
        {
            "bundle_name": "Mobistar_be",
            "sha1": "aaabbd0e9088a11b3ffc52e920ec1f0e8b7a859e",
            "file_size": 20480,
            "created_at": "2025-05-22T19:41:38.331551+00:00"
        },
        {
            "bundle_name": "KPN_Telfort_nl",
            "sha1": "f7562bde03634a8ce5d009ce1314a07ad1446ce6",
            "file_size": 20480,
            "created_at": "2025-05-22T19:41:38.332617+00:00"
        },
        {
            "bundle_name": "STC_sa",
            "sha1": "f9dc094c58353ade1ebeed61aceee7e11d73fa7d",
            "file_size": 20480,
            "created_at": "2025-05-22T19:41:38.334224+00:00"
        },
        {
            "bundle_name": "Orange_uk",
            "sha1": "67b3ffcaf0ce36d89324fd48b2234b072fbf7d15",
            "file_size": 40960,
            "created_at": "2025-05-22T19:41:38.338150+00:00"
        },
        {
            "bundle_name": "Telenor_pk",
            "sha1": "15506b7156393ae70d0bad2119203fab8018721f",
            "file_size": 20480,
            "created_at": "2025-05-22T19:41:38.341063+00:00"
        },
        {
            "bundle_name": "Sprint_CSIM_LTE_US",
            "sha1": "6c69e8acd6c861ea74ba677e20f784d99dd150e8",
            "file_size": 40960,
            "created_at": "2025-05-22T19:41:38.344822+00:00"
        },
        {
            "bundle_name": "EPlus_de",
            "sha1": "7166beabe3cf1ae830cbce26bc7e849c73d8c19d",
            "file_size": 20480,
            "created_at": "2025-05-22T19:41:38.346461+00:00"
        },
        {
            "bundle_name": "Tango_lu",
            "sha1": "2da6424d3d7cc07c72077e5b1695906c6fd098e3",
            "file_size": 20480,
            "created_at": "2025-05-22T19:41:38.348448+00:00"
        },
        {
            "bundle_name": "RoamMobility_US",
            "sha1": "9fe7aece1a81e75bd12d62763689a1c9bd968d3c",
            "file_size": 20480,
            "created_at": "2025-05-22T19:41:38.351125+00:00"
        },
        {
            "bundle_name": "Reliance_RTL_in",
            "sha1": "f38b19e8017efbac5a7bc55573b788b9f5dbd32f",
            "file_size": 20480,
            "created_at": "2025-05-22T19:41:38.353997+00:00"
        },
        {
            "bundle_name": "Orange_ro",
            "sha1": "700da29e00e75e353c4bf529132d658886347b73",
            "file_size": 20480,
            "created_at": "2025-05-22T19:41:38.357018+00:00"
        },
        {
            "bundle_name": "Claro_pe",
            "sha1": "65ed940e0c4a4f15a8e6880a1af7a6714c6d91c5",
            "file_size": 20480,
            "created_at": "2025-05-22T19:41:38.360145+00:00"
        },
        {
            "bundle_name": "Sasktel_ca",
            "sha1": "d975d430d912dc3a71ae9f80a25d487bff6ff528",
            "file_size": 20480,
            "created_at": "2025-05-22T19:41:38.363099+00:00"
        }
    ],
    "updated_at": "2025-05-22T19:41:38.492244+00:00"
}